{
    "@class": "com.kony.gen.viz.model.component.KVizImage2",
    "DNDConfig": null,
    "_base64_": null,
    "_height_": {
        "type": "string",
        "value": "50dp"
    },
    "_left_": {
        "type": "string",
        "value": "83dp"
    },
    "_margin_": [
        0,
        0,
        0,
        0
    ],
    "_padding_": [
        0,
        0,
        0,
        0
    ],
    "_skin_": "s035175908f548c6903c3efdb8fd100c",
    "_src_": "successlogo_1_1.png",
    "_top_": {
        "type": "string",
        "value": "41dp"
    },
    "_width_": {
        "type": "string",
        "value": "50dp"
    },
    "canUpdateUI": true,
    "centerx": {
        "type": "string",
        "value": "50%"
    },
    "containerweight": 100,
    "id": "imgSuccessLogo",
    "imagescalemode": 1,
    "info": null,
    "invokedProperty": "src",
    "iscustomlayout": false,
    "isvisible": true,
    "kuid": "bb450b4398fb41ab9df27664dc988f9d",
    "name": "kony.ui.Image2",
    "parent": "flexSuccessAlert",
    "pf": "frmAddRecipient",
    "retaincontentalignment": false,
    "retainflexpositionproperties": false,
    "srcType": 1,
    "wType": "Image",
    "widgetalignment": 5,
    "zindex": 1
}